Metadata-Version: 2.1
Name: odoo14-addon-printing_auto_stock_picking
Version: 14.0.1.1.2.dev2
Summary: Printing Auto Stock Picking
Home-page: https://github.com/OCA/stock-logistics-reporting
Author: BCIM, MT Software, Odoo Community Association (OCA)
Author-email: support@odoo-community.org
License: AGPL-3
Classifier: Programming Language :: Python
Classifier: Framework :: Odoo
Classifier: Framework :: Odoo :: 14.0
Classifier: License :: OSI Approved :: GNU Affero General Public License v3
Requires-Python: >=3.6
Requires-Dist: odoo14-addon-printing-auto-base
Requires-Dist: odoo<14.1dev,>=14.0a
